yolo_easy_augmentation/__init__.py
yolo_easy_augmentation/yolo_easy_augmentation.py
yolo_easy_augmentation-1.0.7.dist-info/LICENSE.txt
yolo_easy_augmentation-1.0.7.dist-info/METADATA
yolo_easy_augmentation-1.0.7.dist-info/WHEEL
yolo_easy_augmentation-1.0.7.dist-info/top_level.txt
yolo_easy_augmentation-1.0.7.dist-info/RECORD
